{
  "description": "The emergence of Git centered workflows, around modern build tools, static site generators, and modern browsers, have changed the way most front-enders work.\n\nMatt Biilmann will cover how a new stack is emerging and how this will change how web sites and web apps are built in the future.",
  "duration": 1827,
  "id": "uWTMEDEPw8c",
  "publishedAt": 1495831259,
  "ranking": {
    "likes": 324,
    "views": 15098
  },
  "tags": ["JAMstack", "Git", "site generators"],
  "thumbnails": {
    "huge": "https://i.ytimg.com/vi/uWTMEDEPw8c/maxresdefault.jpg",
    "large": "https://i.ytimg.com/vi/uWTMEDEPw8c/sddefault.jpg",
    "medium": "https://i.ytimg.com/vi/uWTMEDEPw8c/hqdefault.jpg",
    "small": "https://i.ytimg.com/vi/uWTMEDEPw8c/mqdefault.jpg",
    "tiny": "https://i.ytimg.com/vi/uWTMEDEPw8c/default.jpg"
  },
  "title": "Rise of the JAMstack — Mathias Biillman"
}
